[
  {
    "site_key": "almaty",
    "site_name": "Almaty \u2014 Medeu/Dostyk Embassy Row",
    "patch_id": "SE",
    "patch_label": "SE Courtyard",
    "lat": 43.246491,
    "lon": 76.950047,
    "grade_short": "C",
    "grade": "C  Moderate   -- improvements recommended",
    "composite": 35.0,
    "wind_score": 100.0,
    "solar_score": 0.0,
    "utci_score": 0.0,
    "wind_val": 0.782,
    "solar_val": 0.018,
    "utci_val": 0.0,
    "wind_stat_label": "Wind trap",
    "solar_stat_label": "Solar deficit",
    "utci_stat_label": "Cold stress",
    "rank": 1
  },
  {
    "site_key": "almaty",
    "site_name": "Almaty \u2014 Medeu/Dostyk Embassy Row",
    "patch_id": "CTR",
    "patch_label": "Central Courtyard",
    "lat": 43.244996,
    "lon": 76.947994,
    "grade_short": "B",
    "grade": "B  Fair       -- minor enhancements worthwhile",
    "composite": 33.4,
    "wind_score": 95.5,
    "solar_score": 0.0,
    "utci_score": 0.0,
    "wind_val": 0.575,
    "solar_val": 0.04,
    "utci_val": 0.0,
    "wind_stat_label": "Wind trap",
    "solar_stat_label": "Solar deficit",
    "utci_stat_label": "Cold stress",
    "rank": 2
  },
  {
    "site_key": "almaty",
    "site_name": "Almaty \u2014 Medeu/Dostyk Embassy Row",
    "patch_id": "SW",
    "patch_label": "SW Courtyard",
    "lat": 43.246491,
    "lon": 76.945941,
    "grade_short": "B",
    "grade": "B  Fair       -- minor enhancements worthwhile",
    "composite": 22.9,
    "wind_score": 65.5,
    "solar_score": 0.0,
    "utci_score": 0.0,
    "wind_val": 0.41,
    "solar_val": 0.04,
    "utci_val": 0.0,
    "wind_stat_label": "Wind trap",
    "solar_stat_label": "Solar deficit",
    "utci_stat_label": "Cold stress",
    "rank": 3
  },
  {
    "site_key": "almaty",
    "site_name": "Almaty \u2014 Medeu/Dostyk Embassy Row",
    "patch_id": "NE",
    "patch_label": "NE Courtyard",
    "lat": 43.2435,
    "lon": 76.950047,
    "grade_short": "A",
    "grade": "A  Good       -- no urgent intervention needed",
    "composite": 4.4,
    "wind_score": 12.4,
    "solar_score": 0.0,
    "utci_score": 0.0,
    "wind_val": 0.118,
    "solar_val": 0.066,
    "utci_val": 0.0,
    "wind_stat_label": "Wind trap",
    "solar_stat_label": "Solar deficit",
    "utci_stat_label": "Cold stress",
    "rank": 4
  },
  {
    "site_key": "almaty",
    "site_name": "Almaty \u2014 Medeu/Dostyk Embassy Row",
    "patch_id": "NW",
    "patch_label": "NW Courtyard",
    "lat": 43.2435,
    "lon": 76.945941,
    "grade_short": "A",
    "grade": "A  Good       -- no urgent intervention needed",
    "composite": 3.8,
    "wind_score": 11.0,
    "solar_score": 0.0,
    "utci_score": 0.0,
    "wind_val": 0.11,
    "solar_val": 0.064,
    "utci_val": 0.0,
    "wind_stat_label": "Wind trap",
    "solar_stat_label": "Solar deficit",
    "utci_stat_label": "Cold stress",
    "rank": 5
  }
]